terminalgpt/__init__.py
terminalgpt/chat.py
terminalgpt/config.py
terminalgpt/conversations.py
terminalgpt/encryption.py
terminalgpt/main.py
terminalgpt/printer.py
tests/__init__.py
tests/e2e/test_new_e2e.py
tests/integration/test_load_integration.py
tests/integration/test_new_integration.py
tests/unit/mocks.py
tests/unit/test_chat.py
tests/unit/test_conversations.py
tests/unit/test_load_unit.py
tests/unit/test_printer.py
Terminalgemini-2.0.3.dist-info/LICENSE
Terminalgemini-2.0.3.dist-info/METADATA
Terminalgemini-2.0.3.dist-info/WHEEL
Terminalgemini-2.0.3.dist-info/entry_points.txt
Terminalgemini-2.0.3.dist-info/top_level.txt
Terminalgemini-2.0.3.dist-info/RECORD
