Metadata-Version: 2.1
Name: Terminalgemini
Version: 2.0.3
Summary: AI chat assistant in your terminal powered by Gemini models.
Author: ticklecatisback
Author-email: alesaholder@gmail.com
Classifier: Development Status :: 4 - Beta
Classifier: Intended Audience :: Developers
Classifier: Topic :: Software Development :: Build Tools
Classifier: License :: OSI Approved :: MIT License
Classifier: Programming Language :: Python :: 3
Classifier: Programming Language :: Python :: 3.9
Requires-Python: >=3.10
License-File: LICENSE
Requires-Dist: google-generativeai
Requires-Dist: tiktoken
Requires-Dist: colorama
Requires-Dist: cryptography
Requires-Dist: click
Requires-Dist: prompt-toolkit
Requires-Dist: yaspin
Requires-Dist: rich
Requires-Dist: isort
Requires-Dist: pytest
Requires-Dist: pylint
